sceneprogllm/__init__.py
sceneprogllm/image_helper.py
sceneprogllm/llm.py
sceneprogllm/template.py
sceneprogllm/text2x.py
sceneprogllm-0.3.0.dist-info/METADATA
sceneprogllm-0.3.0.dist-info/WHEEL
sceneprogllm-0.3.0.dist-info/top_level.txt
sceneprogllm-0.3.0.dist-info/RECORD
