Metadata-Version: 2.4
Name: sceneprogllm
Version: 0.3.0
Summary: An LLM wrapper built for scene prog projects
Home-page: https://github.com/KunalMGupta/sceneprogllm.git
Author: Kunal Gupta
Author-email: k5upta@ucsd.edu
Classifier: Programming Language :: Python :: 3
Classifier: License :: OSI Approved :: MIT License
Classifier: Operating System :: OS Independent
Requires-Python: >=3.11
Requires-Dist: langchain
Requires-Dist: langchain-openai
Requires-Dist: dotenv
Requires-Dist: openai
Requires-Dist: langchain-community
Requires-Dist: Pillow
Requires-Dist: numpy
Dynamic: author
Dynamic: author-email
Dynamic: classifier
Dynamic: description
Dynamic: description-content-type
Dynamic: home-page
Dynamic: requires-dist
Dynamic: requires-python
Dynamic: summary
